[{"id":"9","unit":"3","remark":"","create_date":"2023-11-03","create_time":"12:24:18","create_by":"5","update_date":null,"update_time":null,"update_by":null,"status":"A"},{"id":"6","unit":"IND","remark":"in","create_date":"2023-10-13","create_time":"12:39:27","create_by":"4","update_date":"2023-10-13","update_time":"12:39:33","update_by":"4","status":"A"},{"id":"5","unit":"YEN","remark":"Japan","create_date":"2023-08-11","create_time":"10:11:16","create_by":"1","update_date":"2023-09-06","update_time":"15:59:06","update_by":"1","status":"A"},{"id":"4","unit":"USD","remark":"United State Dollar","create_date":"2023-08-10","create_time":"16:37:32","create_by":"1","update_date":"2023-08-10","update_time":"16:37:32","update_by":null,"status":"A"},{"id":"3","unit":"HKD","remark":"Hong Kong Dollar","create_date":"2023-08-10","create_time":"16:36:53","create_by":"1","update_date":"2023-08-10","update_time":"16:37:41","update_by":"1","status":"A"},{"id":"2","unit":"MYR","remark":"Malaysia Ringgit","create_date":"2023-08-10","create_time":"16:35:55","create_by":"1","update_date":"2023-08-10","update_time":"16:37:54","update_by":"1","status":"A"},{"id":"1","unit":"SGD","remark":"Singapore Dollar","create_date":"2023-08-10","create_time":"16:34:54","create_by":"1","update_date":"2023-08-10","update_time":"16:37:59","update_by":"1","status":"A"}]