[{"id":"13","name":"231123","num_of_days":"3123","leave_status":"Active","create_date":"2023-11-06","create_time":"12:44:41","create_by":"5","update_date":null,"update_time":null,"update_by":null,"status":"A","auto_assign":"no"},{"id":"12","name":"sfddsfsd","num_of_days":"312312","leave_status":"Active","create_date":"2023-11-06","create_time":"12:44:33","create_by":"5","update_date":null,"update_time":null,"update_by":null,"status":"A","auto_assign":"yes"},{"id":"11","name":"3123","num_of_days":"123","leave_status":"Active","create_date":"2023-11-06","create_time":"12:29:17","create_by":"5","update_date":null,"update_time":null,"update_by":null,"status":"A","auto_assign":"no"},{"id":"10","name":"2","num_of_days":"12312","leave_status":"Active","create_date":"2023-11-06","create_time":"12:28:44","create_by":"5","update_date":null,"update_time":null,"update_by":null,"status":"A","auto_assign":"no"},{"id":"8","name":"321","num_of_days":"3123","leave_status":"Active","create_date":"2023-11-06","create_time":"11:35:58","create_by":"5","update_date":null,"update_time":null,"update_by":null,"status":"A","auto_assign":"yes"},{"id":"3","name":"3213","num_of_days":"3","leave_status":"Active","create_date":"2023-11-03","create_time":"12:29:17","create_by":"5","update_date":null,"update_time":null,"update_by":null,"status":"A","auto_assign":"no"}]
